kipoi_conda/__init__.py
kipoi_conda/_version.py
kipoi_conda/dependencies.py
kipoi_conda/utils.py
kipoi_conda-0.3.1.dist-info/LICENSE
kipoi_conda-0.3.1.dist-info/METADATA
kipoi_conda-0.3.1.dist-info/WHEEL
kipoi_conda-0.3.1.dist-info/top_level.txt
kipoi_conda-0.3.1.dist-info/RECORD
