Metadata-Version: 2.1
Name: kipoi-conda
Version: 0.3.1
Summary: kipoi-conda: conda/pip related functionality used by Kipoi
Home-page: https://github.com/kipoi/kipoi-conda
Author: Kipoi team
Author-email: avsec@in.tum.de
License: MIT license
Keywords: model zoo,deep learning,computational biology,bioinformatics,genomics
Platform: UNKNOWN
License-File: LICENSE
Requires-Dist: related
Requires-Dist: kipoi-utils (>=0.3.0)
Provides-Extra: develop
Requires-Dist: bumpversion ; extra == 'develop'
Requires-Dist: wheel ; extra == 'develop'
Requires-Dist: pytest (>=3.3.1) ; extra == 'develop'
Requires-Dist: pytest-xdist ; extra == 'develop'
Requires-Dist: pytest-pep8 ; extra == 'develop'
Requires-Dist: pytest-cov ; extra == 'develop'
Requires-Dist: coveralls ; extra == 'develop'
Requires-Dist: numpy ; extra == 'develop'
Requires-Dist: pandas (>=0.21.0) ; extra == 'develop'
